XStatic_Tablesorter_Mottie-2.10.8.1-py3.13-nspkg.pth
xstatic/pkg/tablesorter_mottie/__init__.py
xstatic/pkg/tablesorter_mottie/data/css/filter.formatter.css
xstatic/pkg/tablesorter_mottie/data/css/theme.black-ice.css
xstatic/pkg/tablesorter_mottie/data/css/theme.blue.css
xstatic/pkg/tablesorter_mottie/data/css/theme.bootstrap.css
xstatic/pkg/tablesorter_mottie/data/css/theme.dark.css
xstatic/pkg/tablesorter_mottie/data/css/theme.default.css
xstatic/pkg/tablesorter_mottie/data/css/theme.dropbox.css
xstatic/pkg/tablesorter_mottie/data/css/theme.green.css
xstatic/pkg/tablesorter_mottie/data/css/theme.grey.css
xstatic/pkg/tablesorter_mottie/data/css/theme.ice.css
xstatic/pkg/tablesorter_mottie/data/css/theme.jui.css
xstatic/pkg/tablesorter_mottie/data/css/theme.less
xstatic/pkg/tablesorter_mottie/data/css/images/black-asc.gif
xstatic/pkg/tablesorter_mottie/data/css/images/black-desc.gif
xstatic/pkg/tablesorter_mottie/data/css/images/black-unsorted.gif
xstatic/pkg/tablesorter_mottie/data/css/images/dropbox-asc-hovered.png
xstatic/pkg/tablesorter_mottie/data/css/images/dropbox-asc.png
xstatic/pkg/tablesorter_mottie/data/css/images/dropbox-desc-hovered.png
xstatic/pkg/tablesorter_mottie/data/css/images/dropbox-desc.png
xstatic/pkg/tablesorter_mottie/data/css/images/green-asc.gif
xstatic/pkg/tablesorter_mottie/data/css/images/green-desc.gif
xstatic/pkg/tablesorter_mottie/data/css/images/green-header.gif
xstatic/pkg/tablesorter_mottie/data/css/images/green-unsorted.gif
xstatic/pkg/tablesorter_mottie/data/css/images/ice-asc.gif
xstatic/pkg/tablesorter_mottie/data/css/images/ice-desc.gif
xstatic/pkg/tablesorter_mottie/data/css/images/ice-unsorted.gif
xstatic/pkg/tablesorter_mottie/data/css/images/white-asc.gif
xstatic/pkg/tablesorter_mottie/data/css/images/white-desc.gif
xstatic/pkg/tablesorter_mottie/data/css/images/white-unsorted.gif
xstatic/pkg/tablesorter_mottie/data/css/psd/green-asc.psd
xstatic/pkg/tablesorter_mottie/data/css/psd/green-desc.psd
xstatic_tablesorter_mottie-2.10.8.1.dist-info/METADATA
xstatic_tablesorter_mottie-2.10.8.1.dist-info/WHEEL
xstatic_tablesorter_mottie-2.10.8.1.dist-info/namespace_packages.txt
xstatic_tablesorter_mottie-2.10.8.1.dist-info/top_level.txt
xstatic_tablesorter_mottie-2.10.8.1.dist-info/RECORD
