Metadata-Version: 2.4
Name: XStatic-Tablesorter-Mottie
Version: 2.10.8.1
Summary: Tablesorter-Mottie 2.10.8 (XStatic packaging standard)
Home-page: https://github.com/Mottie/tablesorter/
Maintainer: Cheer Xiao
Maintainer-email: xiaqqaix@gmail.com
License: (same as Tablesorter-Mottie)
Keywords: tablesorter_mottie xstatic
Platform: any
Dynamic: description
Dynamic: home-page
Dynamic: keywords
Dynamic: license
Dynamic: maintainer
Dynamic: maintainer-email
Dynamic: platform
Dynamic: summary
